README.rst
ez_setup.py
setup.py
msync/__init__.py
msync/sync.py
msync/version.py
msync.egg-info/PKG-INFO
msync.egg-info/SOURCES.txt
msync.egg-info/dependency_links.txt
msync.egg-info/entry_points.txt
msync.egg-info/requires.txt
msync.egg-info/top_level.txt