Metadata-Version: 1.1
Name: msync
Version: 1.0.0
Summary: A command line utility for one shot upload of a directory tree to dropbox.
Home-page: http://pypi.python.org/pypi/msync/
Author: Amol Umrale
Author-email: babaiscool@gmail.com
License: UNKNOWN
Platform: UNKNOWN
Classifier: Development Status :: 4 - Beta
Classifier: Environment :: Console
Classifier: License :: OSI Approved :: MIT License
Classifier: Natural Language :: English
Classifier: Operating System :: POSIX :: Linux
Classifier: Programming Language :: Python :: 2.7
